cli_wizard/__init__.py
cli_wizard/cli.py
cli_wizard/constants.py
cli_wizard/commands/__init__.py
cli_wizard/commands/common.py
cli_wizard/commands/config.py
cli_wizard/commands/generate.py
cli_wizard/config/__init__.py
cli_wizard/config/configuration.py
cli_wizard/config/default_config.yaml
cli_wizard/config/schema.py
cli_wizard/generator/__init__.py
cli_wizard/generator/generator.py
cli_wizard/generator/models.py
cli_wizard/generator/parser.py
cli_wizard/templates/README.md.j2
cli_wizard/templates/cli.py.j2
cli_wizard/templates/client.py.j2
cli_wizard/templates/command_group.py.j2
cli_wizard/templates/commands_config.py.j2
cli_wizard/templates/commands_init.py.j2
cli_wizard/templates/constants.py.j2
cli_wizard/templates/logging.py.j2
cli_wizard/templates/package_init.py.j2
cli_wizard/templates/profile.py.j2
cli_wizard/templates/pyproject.toml.j2
cli_wizard-1.0.0.dist-info/licenses/LICENSE
cli_wizard-1.0.0.dist-info/METADATA
cli_wizard-1.0.0.dist-info/WHEEL
cli_wizard-1.0.0.dist-info/entry_points.txt
cli_wizard-1.0.0.dist-info/top_level.txt
cli_wizard-1.0.0.dist-info/RECORD
