Metadata-Version: 2.4
Name: cli-wizard
Version: 1.0.0
Summary: Generate modern CLIs from OpenAPI specifications
Author-email: Giacomo Marciani <giacomo.marciani@gmail.com>
License: MIT
Project-URL: Homepage, https://github.com/gmarciani/cli-wizard
Project-URL: Repository, https://github.com/gmarciani/cli-wizard
Project-URL: Issues, https://github.com/gmarciani/cli-wizard/issues
Classifier: Development Status :: 5 - Production/Stable
Classifier: Intended Audience :: Developers
Classifier: License :: OSI Approved :: MIT License
Classifier: Programming Language :: Python :: 3
Classifier: Programming Language :: Python :: 3.12
Classifier: Programming Language :: Python :: 3.13
Classifier: Programming Language :: Python :: 3.14
Requires-Python: >=3.12
License-File: LICENSE
Requires-Dist: click~=8.1
Requires-Dist: Jinja2~=3.1
Requires-Dist: pydantic~=2.10
Requires-Dist: PyYAML~=6.0
Requires-Dist: requests~=2.32
Provides-Extra: dev
Requires-Dist: autoflake~=2.3; extra == "dev"
Requires-Dist: black~=26.1; extra == "dev"
Requires-Dist: build~=1.3; extra == "dev"
Requires-Dist: flake8~=7.3; extra == "dev"
Requires-Dist: mypy~=1.18; extra == "dev"
Requires-Dist: pre-commit~=4.0; extra == "dev"
Requires-Dist: pytest~=9.0; extra == "dev"
Requires-Dist: pytest-cov~=7.0; extra == "dev"
Requires-Dist: tox~=4.32; extra == "dev"
Requires-Dist: twine~=6.2; extra == "dev"
Requires-Dist: types-PyYAML~=6.0; extra == "dev"
Requires-Dist: types-requests~=2.32; extra == "dev"
Provides-Extra: docs
Requires-Dist: sphinx~=9.1; extra == "docs"
Requires-Dist: sphinx-click~=6.0; extra == "docs"
Requires-Dist: sphinx-rtd-theme~=3.0; extra == "docs"
Dynamic: license-file
